pgsqlite/__init__.py
pgsqlite/pgsqlite.py
pgsqlite-1.0.3.dist-info/LICENSE
pgsqlite-1.0.3.dist-info/METADATA
pgsqlite-1.0.3.dist-info/WHEEL
pgsqlite-1.0.3.dist-info/top_level.txt
pgsqlite-1.0.3.dist-info/RECORD
