Metadata-Version: 2.1
Name: pgsqlite
Version: 1.0.3
Summary: Loader to import sqlite3 databases into Postgres
Home-page: https://github.com/bitdotioinc/pgsqlite
Author: bit.io
Author-email: python@bit.io
License: UNKNOWN
Project-URL: Bug Tracker, https://github.com/bitdotioinc/pgsqlite/issues
Keywords: bit.io,Database,postgres,postgresql,sqlite,sqlite3
Platform: UNKNOWN
Classifier: Programming Language :: Python :: 3
Classifier: Operating System :: OS Independent
Requires-Python: >=3.9
License-File: LICENSE
Requires-Dist: sqlite-utils (>=3.28)
Requires-Dist: psycopg (>=3.1)
Requires-Dist: psycopg-binary (>=3.1)
Requires-Dist: structlog (>=22.1.0)
Requires-Dist: sqlglot (>=10.6.3)
